setup.py
wppy.py
wppy.egg-info/PKG-INFO
wppy.egg-info/SOURCES.txt
wppy.egg-info/dependency_links.txt
wppy.egg-info/not-zip-safe
wppy.egg-info/requires.txt
wppy.egg-info/top_level.txt