Metadata-Version: 1.0
Name: wppy
Version: 1.20
Summary: wppy is a tool to get the latest version of Wordpress and install and configure it for you in one-line command.
Home-page: https://github.com/halilkaya/wppy
Author: Halil Kaya
Author-email: kayahalil@gmail.com
License: GPLv3
Platform: UNKNOWN
